toolbox/__init__.py
toolbox/portfolio.py
toolbox/stats.py
toolbox/utils.py
toolbox/version.py
zen_toolbox-0.1.70.dist-info/METADATA
zen_toolbox-0.1.70.dist-info/WHEEL
zen_toolbox-0.1.70.dist-info/entry_points.txt
zen_toolbox-0.1.70.dist-info/top_level.txt
zen_toolbox-0.1.70.dist-info/RECORD
