Metadata-Version: 2.1
Name: zen-toolbox
Version: 0.1.70
Summary: financial analysis toolbox
Home-page: https://github.com/zegoverno/zen-toolbox
Author: Zé Governo
Author-email: zegoverno@hey.com
License: Apache Software License
Keywords: quant finance analysis portfolio
Platform: any
Classifier: Programming Language :: Python :: 3
Classifier: License :: OSI Approved :: Apache Software License
Classifier: Operating System :: OS Independent
Requires-Python: >=3.6
Requires-Dist: numpy (>=1.16.5)
Requires-Dist: pandas (>=0.24.0)
Requires-Dist: scipy (>=1.2.0)
